adaptive_oscillator/__init__.py
adaptive_oscillator/__main__.py
adaptive_oscillator/base_classes.py
adaptive_oscillator/controller.py
adaptive_oscillator/definitions.py
adaptive_oscillator/log_files/__init__.py
adaptive_oscillator/log_files/joint_angles.py
adaptive_oscillator/log_files/main.py
adaptive_oscillator/log_files/parser.py
adaptive_oscillator/oscillator.py
adaptive_oscillator/utils/__init__.py
adaptive_oscillator/utils/log_utils.py
adaptive_oscillator/utils/plot_utils.py
adaptive_oscillator/utils/time_utils.py
adaptive_oscillator-0.2.1.dist-info/METADATA
adaptive_oscillator-0.2.1.dist-info/WHEEL
adaptive_oscillator-0.2.1.dist-info/licenses/LICENSE
adaptive_oscillator-0.2.1.dist-info/RECORD
